project_generator/__init__.py
project_generator/__main__.py
project_generator/_version.py
project_generator/generate.py
project_generator/init_yaml.py
project_generator/project.py
project_generator/run.py
project_generator/settings.py
project_generator/tools_supported.py
project_generator/util.py
project_generator/commands/__init__.py
project_generator/commands/build.py
project_generator/commands/clean.py
project_generator/commands/generate.py
project_generator/commands/init.py
project_generator/commands/list_projects.py
project_generator/templates/cmakelist_armcc.tmpl
project_generator/templates/cmakelist_armcc_workspace.tmpl
project_generator/templates/cmakelist_armclang.tmpl
project_generator/templates/cmakelist_armclang_workspace.tmpl
project_generator/templates/cmakelist_gccarm.tmpl
project_generator/templates/cmakelist_gccarm_workspace.tmpl
project_generator/templates/coide.coproj.tmpl
project_generator/templates/eclipse.project.tmpl
project_generator/templates/eclipse_makefile.cproject.tmpl
project_generator/templates/gdb.tmpl
project_generator/templates/iar.ewd
project_generator/templates/iar.ewp
project_generator/templates/iar.eww
project_generator/templates/makefile.tmpl
project_generator/templates/makefile_armcc.tmpl
project_generator/templates/makefile_armclang.tmpl
project_generator/templates/makefile_gcc.tmpl
project_generator/templates/makefile_llvm.tmpl
project_generator/templates/makefile_workspace.tmpl
project_generator/templates/sublimetext.sublime-project.tmpl
project_generator/templates/uvision.uvmpw
project_generator/templates/uvision.uvoptx
project_generator/templates/uvision.uvproj
project_generator/templates/visual_studio.vcxproj.filters.tmpl
project_generator/templates/visual_studio.vcxproj.tmpl
project_generator/tools/__init__.py
project_generator/tools/cmake.py
project_generator/tools/cmakearmcc.py
project_generator/tools/cmakearmclang.py
project_generator/tools/cmakegccarm.py
project_generator/tools/coide.py
project_generator-0.12.0.dist-info/LICENSE
project_generator-0.12.0.dist-info/METADATA
project_generator-0.12.0.dist-info/WHEEL
project_generator-0.12.0.dist-info/entry_points.txt
project_generator-0.12.0.dist-info/top_level.txt
project_generator-0.12.0.dist-info/zip-safe
project_generator-0.12.0.dist-info/RECORD
