Metadata-Version: 2.1
Name: project-generator
Version: 0.12.0
Summary: Project generators for various embedded tools (IDE). IAR, uVision, Makefile and many more in the roadmap!
Home-page: https://github.com/project-generator/project_generator
Maintainer: Martin Kojtal
Maintainer-email: c0170@rocketmail.com
License: Apache 2.0
Project-URL: Home, https://github.com/project-generator/project_generator
Project-URL: Issues, https://github.com/project-generator/project_generator/issues
Project-URL: Documentation, https://github.com/project-generator/project_generator/wiki
Keywords: c cpp project generator embedded
Classifier: Development Status :: 4 - Beta
Classifier: Intended Audience :: Developers
Classifier: Environment :: Console
Classifier: License :: OSI Approved :: Apache Software License
Classifier: Operating System :: MacOS
Classifier: Operating System :: Microsoft :: Windows
Classifier: Operating System :: POSIX
Classifier: Operating System :: Unix
Classifier: Programming Language :: Python
Classifier: Programming Language :: C
Classifier: Programming Language :: C++
Classifier: Topic :: Software Development
Classifier: Topic :: Software Development :: Embedded Systems
License-File: LICENSE
Requires-Dist: pyyaml (<7.0,>=6.0)
Requires-Dist: Jinja2 (<4.0,>=3.0)
Requires-Dist: xmltodict
Requires-Dist: project-generator-definitions (<0.3.0,>=0.2.2)
